{
    "translations": {
        "de": {
            "Apikey": "Api-Key",
            "Speech language": "Sprache",
            "German": "Deutsch",
            "Speech rate (speed)": "Sprachgeschwindigkeit",
            "Speech voice (empty for default voice)": "Stimme (leer für standard Stimme)",
            "Codec": "Format",
            "Samplerate": "Samplerate",
            "active": "Aktiv",
            "no Api-Key": "Kein Api-Key gesetzt",
            "Get your plan for Text-to-speech Online Services at: https://www.voicerss.org/pricing/": "Holen Sie sich Ihren Plan für Text-to-Speech Online-Dienste unter: https://www.voicerss.org/pricing/",
            "This module is free for non-commercial use,\r\nDonations in support of the author are accepted here:": "Dieses Modul ist für die nicht kommerzielle Nutzung kostenlos,\r\nSchenkungen als Unterstützung für den Autor werden hier akzeptiert:"
        }
    }
}